{
  "kind": "collectionType",
  "collectionName": "experts",
  "info": {
    "name": "Expert",
    "description": ""
  },
  "options": {
    "increments": true,
    "timestamps": true,
    "draftAndPublish": true
  },
  "pluginOptions": {},
  "attributes": {
    "Name": {
      "type": "string"
    },
    "Description": {
      "type": "text"
    },
    "Price": {
      "type": "biginteger"
    },
    "img": {
      "model": "file",
      "via": "related",
      "allowedTypes": [
        "images",
        "files",
        "videos"
      ],
      "plugin": "upload",
      "required": false,
      "pluginOptions": {}
    }
  }
}
